misery/__init__.py
misery/clickhouse.py
misery/core.py
misery/dictionary.py
misery/postgres.py
misery-0.7.0.dist-info/LICENSE
misery-0.7.0.dist-info/WHEEL
misery-0.7.0.dist-info/METADATA
misery-0.7.0.dist-info/RECORD
