Metadata-Version: 2.1
Name: misery
Version: 0.7.0
Summary: asyncio-friendly database toolkit
Author: Anton Evdokimov
Author-email: meowmeowcode@gmail.com
Requires-Python: >=3.8
Classifier: Programming Language :: Python :: 3
Classifier: Programming Language :: Python :: 3.10
Classifier: Programming Language :: Python :: 3.8
Classifier: Programming Language :: Python :: 3.9
Provides-Extra: clickhouse
Provides-Extra: postgres
Requires-Dist: PyPika (>=0.48.9,<0.49.0); extra == "postgres" or extra == "clickhouse"
Requires-Dist: aiohttp (>=3.8.1,<4.0.0); extra == "clickhouse"
Requires-Dist: asyncpg (>=0.25.0,<0.26.0); extra == "postgres"
Requires-Dist: ipaddress (>=1.0.23,<2.0.0)
